dbop/__init__.py
dbop/dbop.py
dbop-0.0.0.2.dist-info/DESCRIPTION.rst
dbop-0.0.0.2.dist-info/METADATA
dbop-0.0.0.2.dist-info/RECORD
dbop-0.0.0.2.dist-info/WHEEL
dbop-0.0.0.2.dist-info/entry_points.txt
dbop-0.0.0.2.dist-info/metadata.json
dbop-0.0.0.2.dist-info/top_level.txt
