Metadata-Version: 2.0
Name: dbop
Version: 0.0.0.2
Summary: mysql operate
Home-page: http://www.zhaomingming.cn
Author: zhaomingming
Author-email: 13271929138@163.com
License: MIT
Platform: any
Provides-Extra: dev
Requires-Dist: check-manifest; extra == 'dev'
Provides-Extra: test
Requires-Dist: coverage; extra == 'test'
